[{ "email": "hangthutimviec365@gmail.com", "code": "vetinh410", "for": "vetinh", "apiKey": "AIzaSyDfXGNCVy-nLjfaqRyxVxIug7ln2FMChXY", "authDomain": "vetinh410.firebaseapp.com", "projectId": "vetinh410", "storageBucket": "vetinh410.appspot.com", "messagingSenderId": "670983671697", "appId": "1:670983671697:web:f7d0e6f4f049b558395430", "measurementId": "G-WV5X1DSEEK" }, { "email": "hangthutimviec365@gmail.com", "code": "vetinh411", "for": "vetinh", "apiKey": "AIzaSyDynFb5VEOG_5o0u-Gku2f-DYevNlgALbw", "authDomain": "vetinh411.firebaseapp.com", "projectId": "vetinh411", "storageBucket": "vetinh411.appspot.com", "messagingSenderId": "1063041819604", "appId": "1:1063041819604:web:18b6eaff37c524bfa8ac41", "measurementId": "G-P5VPT6K79K" }, { "email": "hangthutimviec365@gmail.com", "code": "vetinh412", "for": "vetinh", "apiKey": "AIzaSyCIpvVkHeNDjj0FScgmZTjCQ3ug9Nu-8fQ", "authDomain": "vetinh412.firebaseapp.com", "projectId": "vetinh412", "storageBucket": "vetinh412.appspot.com", "messagingSenderId": "333537915124", "appId": "1:333537915124:web:e16da8a492070fbecd2ea1", "measurementId": "G-8YXC158KPN" }, { "email": "hangthutimviec365@gmail.com", "code": "vetinh413", "for": "vetinh", "apiKey": "AIzaSyCGQKWGqEFZFeTEIguEFe0qdWDKrFHfvFk", "authDomain": "vetinh413.firebaseapp.com", "projectId": "vetinh413", "storageBucket": "vetinh413.appspot.com", "messagingSenderId": "871316023786", "appId": "1:871316023786:web:777ec484bbb88c65d72a93", "measurementId": "G-FGFLBJ7JF5" }, { "email": "hangthutimviec365@gmail.com", "code": "vetinh414", "for": "vetinh", "apiKey": "AIzaSyD_juSKYOjOw-8v7DssNYVX5KnkSx-ieus", "authDomain": "vetinh414.firebaseapp.com", "projectId": "vetinh414", "storageBucket": "vetinh414.appspot.com", "messagingSenderId": "381140155700", "appId": "1:381140155700:web:2dca9a3831f4d39b49b961", "measurementId": "G-ZZBHBNPCQJ" }, { "email": "hangthutimviec365@gmail.com", "code": "vetinh415", "for": "vetinh", "apiKey": "AIzaSyDZS5p9CK4JDqcrjIQqPSw5gjRaYZEqb6I", "authDomain": "vetinh415.firebaseapp.com", "projectId": "vetinh415", "storageBucket": "vetinh415.appspot.com", "messagingSenderId": "258641100484", "appId": "1:258641100484:web:6559c548cc68909af71391", "measurementId": "G-D459HW67FX" }, { "email": "hangthutimviec365@gmail.com", "code": "vetinh416", "for": "vetinh", "apiKey": "AIzaSyCiGBFWxC_1r24jeiEoEC5eLq4C4-Z5VQQ", "authDomain": "vetinh416.firebaseapp.com", "projectId": "vetinh416", "storageBucket": "vetinh416.appspot.com", "messagingSenderId": "145611492091", "appId": "1:145611492091:web:7627cb60ace42e62473e5e", "measurementId": "G-QEJ178V3MV" }, { "email": "hangthutimviec365@gmail.com", "code": "vetinh417", "for": "vetinh", "apiKey": "AIzaSyA60cFNdRUkb3ONLpQjsWIqiUo4vuJ9Rq0", "authDomain": "vetinh417.firebaseapp.com", "projectId": "vetinh417", "storageBucket": "vetinh417.appspot.com", "messagingSenderId": "355659755625", "appId": "1:355659755625:web:0408039dc1663481bbf2f8", "measurementId": "G-KJXS5RRCWB" }, { "email": "hangthutimviec365@gmail.com", "code": "vetinh418", "for": "vetinh", "apiKey": "AIzaSyCcBVVcNvDT0pKyESYmvfzfXI6pVq4-vWQ", "authDomain": "vetinh418.firebaseapp.com", "projectId": "vetinh418", "storageBucket": "vetinh418.appspot.com", "messagingSenderId": "319214477218", "appId": "1:319214477218:web:6799891170a54473b61cfb", "measurementId": "G-80EHVXSTFP" }, { "email": "hangthutimviec365@gmail.com", "code": "vetinh419", "for": "vetinh", "apiKey": "AIzaSyDtkz1OqjlzEogPwKs_1Cpd76X1swzBTyY", "authDomain": "vetinh419.firebaseapp.com", "projectId": "vetinh419", "storageBucket": "vetinh419.appspot.com", "messagingSenderId": "540633936602", "appId": "1:540633936602:web:a3a400c7216011e315ebe3", "measurementId": "G-GF26QVKXL0" }, { "email": "hangthutimviec365@gmail.com", "code": "vetinh420", "for": "vetinh", "apiKey": "AIzaSyBcRYaKWLq2Sxweyzqo71qJ9Lx3ZhxvSKo", "authDomain": "vetinh420.firebaseapp.com", "projectId": "vetinh420", "storageBucket": "vetinh420.appspot.com", "messagingSenderId": "352367941884", "appId": "1:352367941884:web:3103b31ec3b08b3bae5f79", "measurementId": "G-GTGZSCST0R" }, { "email": "hangthutimviec365@gmail.com", "code": "vetinh421", "for": "vetinh", "apiKey": "AIzaSyDY9jAXaTs74hKHmiOTTq9i479DAR4D64I", "authDomain": "vetinh421.firebaseapp.com", "projectId": "vetinh421", "storageBucket": "vetinh421.appspot.com", "messagingSenderId": "180788614527", "appId": "1:180788614527:web:b982024d0ac735d743364a", "measurementId": "G-QK7F3TMEE7" }, { "email": "phamhang99235567@gmail.com", "code": "vetinh422", "for": "vetinh", "apiKey": "AIzaSyC5oGoDD1QuLuIDQOyiw_lDFqivfSxQRMw", "authDomain": "vetinh422.firebaseapp.com", "projectId": "vetinh422", "storageBucket": "vetinh422.appspot.com", "messagingSenderId": "131522475791", "appId": "1:131522475791:web:36b12bcce26929ebe8707a", "measurementId": "G-Y7JTBNVSKE" }, { "email": "phamhang99235567@gmail.com", "code": "vetinh423", "for": "vetinh", "apiKey": "AIzaSyCzmAf9igAsWCXZ5OA-Oz5Zoq2dF5RTRVQ", "authDomain": "vetinh423.firebaseapp.com", "projectId": "vetinh423", "storageBucket": "vetinh423.appspot.com", "messagingSenderId": "622327743317", "appId": "1:622327743317:web:728a51532c79a236f565dc", "measurementId": "G-GN9LWYHHDT" }, { "email": "phamhang99235567@gmail.com", "code": "vetinh424", "for": "vetinh", "apiKey": "AIzaSyDzoggJCLllyzQwH1mbKYIYnmgAMtvlvIQ", "authDomain": "vetinh424.firebaseapp.com", "projectId": "vetinh424", "storageBucket": "vetinh424.appspot.com", "messagingSenderId": "262458765140", "appId": "1:262458765140:web:6e8913e2670bc0f70262c1", "measurementId": "G-WPC0RNXE7P" }, { "email": "phamhang99235567@gmail.com", "code": "vetinh425", "for": "vetinh", "apiKey": "AIzaSyAM_RsYubF5jMKEONTUwK2q-OwMjU-0NrY", "authDomain": "vetinh425.firebaseapp.com", "projectId": "vetinh425", "storageBucket": "vetinh425.appspot.com", "messagingSenderId": "905816189515", "appId": "1:905816189515:web:501bb9a788b49fe1b0bbce", "measurementId": "G-R6WNQBVZ2X" }, { "email": "phamhang99235567@gmail.com", "code": "vetinh426", "for": "vetinh", "apiKey": "AIzaSyCRrSYwvkdmzrQrCeFHbLxEyn5nonZRpl4", "authDomain": "vetinh426.firebaseapp.com", "projectId": "vetinh426", "storageBucket": "vetinh426.appspot.com", "messagingSenderId": "1053291281568", "appId": "1:1053291281568:web:d78f22decf9dbeaddbddc5", "measurementId": "G-G1WTLQXHGF" }, { "email": "phamhang99235567@gmail.com", "code": "vetinh427", "for": "vetinh", "apiKey": "AIzaSyAT8craymMlaMuMo4vPrAT5JVbSgsTLr3s", "authDomain": "vetinh427.firebaseapp.com", "projectId": "vetinh427", "storageBucket": "vetinh427.appspot.com", "messagingSenderId": "12478539107", "appId": "1:12478539107:web:39d8decc78aac98ae29f56", "measurementId": "G-SE2Y36FGE5" }, { "email": "phamhang99235567@gmail.com", "code": "vetinh428", "for": "vetinh", "apiKey": "AIzaSyBOrRUDftNWqmLLgK88B84hR5v0ZWDFqYM", "authDomain": "vetinh428.firebaseapp.com", "projectId": "vetinh428", "storageBucket": "vetinh428.appspot.com", "messagingSenderId": "535898195969", "appId": "1:535898195969:web:b8702f23812bc6b04d5800", "measurementId": "G-W6T1FG687N" }, { "email": "phamhang99235567@gmail.com", "code": "vetinh429", "for": "vetinh", "apiKey": "AIzaSyCa2klcJFmR_Be20zH2MHAA1ZadG9noyww", "authDomain": "vetinh429-ef254.firebaseapp.com", "projectId": "vetinh429-ef254", "storageBucket": "vetinh429-ef254.appspot.com", "messagingSenderId": "846698539587", "appId": "1:846698539587:web:81329b334b55f7648242f6", "measurementId": "G-S1FQ9D9G10" }, { "email": "phamhang99235567@gmail.com", "code": "vetinh430", "for": "vetinh", "apiKey": "AIzaSyBYuBzFtcCIR60IztRkleHw0FvSp8m4Bs4", "authDomain": "vetinh430.firebaseapp.com", "projectId": "vetinh430", "storageBucket": "vetinh430.appspot.com", "messagingSenderId": "379959325625", "appId": "1:379959325625:web:8b9a2d5a60010f550f7c68", "measurementId": "G-28XNHKDG6C" }, { "email": "phamhang99235567@gmail.com", "code": "vetinh431", "for": "vetinh", "apiKey": "AIzaSyAHS2lBwpkR6R_NBcPLRx9ivqmbTUxusyY", "authDomain": "vetinh431.firebaseapp.com", "projectId": "vetinh431", "storageBucket": "vetinh431.appspot.com", "messagingSenderId": "233123294279", "appId": "1:233123294279:web:04bc9b26f5b336e9475562", "measurementId": "G-57EP5FWK8J" }, { "email": "phamhang99235567@gmail.com", "code": "vetinh432", "for": "vetinh", "apiKey": "AIzaSyAdYBMS_yt8I47Ajc2fG4TBPuYrJZxoo2w", "authDomain": "vetinh432.firebaseapp.com", "projectId": "vetinh432", "storageBucket": "vetinh432.appspot.com", "messagingSenderId": "870570057065", "appId": "1:870570057065:web:900153a5da317ca15231f8", "measurementId": "G-TZ2PR7HLYC" }, { "email": "phamhang99235567@gmail.com", "code": "vetinh433", "for": "vetinh", "apiKey": "AIzaSyC37NZUo3_1WvdokQIOlQLK-y3vnk-PmrU", "authDomain": "vetinh433.firebaseapp.com", "projectId": "vetinh433", "storageBucket": "vetinh433.appspot.com", "messagingSenderId": "382715786674", "appId": "1:382715786674:web:dcb8b5245761bba01fe0ab", "measurementId": "G-JV96GCXV7E" }]